simpleconfigfinder/__init__.py
simpleconfigfinder/configfinder.py
simpleconfigfinder-0.5.1.dist-info/WHEEL
simpleconfigfinder-0.5.1.dist-info/METADATA
simpleconfigfinder-0.5.1.dist-info/RECORD
