Metadata-Version: 2.4
Name: simpleconfigfinder
Version: 0.5.1
Summary: Minimalistic configuration finder with standard Python libraries.
License-Expression: MIT
Requires-Python: >=3.11
Project-URL: Homepage, https://fabfabi.github.io/simpleconfigfinder/
Project-URL: Issues, https://github.com/fabfabi/simpleconfigfinder/issues
Project-URL: Repository, https://github.com/fabfabi/simpleconfigfinder
